reckoner_values/__init__.py
reckoner_values/__main__.py
reckoner_values/cli.py
reckoner_values/collections.py
reckoner_values/git_values.py
reckoner_values/meta.py
reckoner_values/reckoner_file_creator.py
reckoner_values/reckoner_file_updater.py
reckoner_values/s3_values.py
reckoner_values/test.yaml
reckoner_values/yaml_utils.py
reckoner_values/__pycache__/__init__.cpython-37.pyc
reckoner_values/__pycache__/cli.cpython-37.pyc
reckoner_values/__pycache__/collections.cpython-37.pyc
reckoner_values/__pycache__/git_values.cpython-37.pyc
reckoner_values/__pycache__/meta.cpython-37.pyc
reckoner_values/__pycache__/reckoner_file_creator.cpython-37.pyc
reckoner_values/__pycache__/reckoner_file_updater.cpython-37.pyc
reckoner_values/__pycache__/s3_values.cpython-37.pyc
reckoner_values/__pycache__/yaml_utils.cpython-37.pyc
reckoner_values/tests/__init__.py
reckoner_values/tests/git_values_tests.py
reckoner_values/tests/reckoner_file_updater_test.py
reckoner_values/tests/data/autohelm.yaml
reckoner_values-1.1.5.dist-info/METADATA
reckoner_values-1.1.5.dist-info/WHEEL
reckoner_values-1.1.5.dist-info/entry_points.txt
reckoner_values-1.1.5.dist-info/top_level.txt
reckoner_values-1.1.5.dist-info/RECORD
